{
  "id": 2011,
  "name": "深文巧诋",
  "buff": {
    "name": null,
    "desc": null,
    "param": []
  },
  "option": [
    {
      "name": "肤廓",
      "desc": "「战意汹涌」期间，我方全体战技不消耗战技点。角色施放战技或终结技后，每击中1个敌方目标获得1层【热潮】，每层使该角色造成的战技和终结技伤害提高<color=#f29e38ff><unbreak>#1[i]%</unbreak></color>，速度提高<color=#f29e38ff><unbreak>#2[i]%</unbreak></color>，最多叠加<color=#f29e38ff><unbreak>#3[i]</unbreak></color>层。",
      "param": [
        0.04,
        0.04,
        10,
        3
      ]
    },
    {
      "name": "乌有",
      "desc": "「战意汹涌」期间，我方全体造成的追加攻击伤害提高<color=#f29e38ff><unbreak>#1[i]%</unbreak></color>，发动追加攻击后，对每个被攻击的敌方目标及其相邻目标造成固定数值的伤害。",
      "param": [
        0.4,
        0.35,
        2
      ]
    },
    {
      "name": "空头",
      "desc": "「战意汹涌」期间，敌方目标受到的击破伤害提高<color=#f29e38ff><unbreak>#1[i]%</unbreak></color>，我方角色击破敌方目标弱点时，自身行动提前<color=#f29e38ff><unbreak>#2[i]%</unbreak></color>。",
      "param": [
        0.3,
        0.12,
        3
      ]
    }
  ],
  "sub_option": [
    {
      "name": "战技攻击",
      "desc": "我方施放战技攻击敌方目标后，每击中1个敌方目标，使我方额外积累<color=#f29e38ff><unbreak>#1[i]</unbreak></color>点「战意值」。",
      "param": [
        5
      ]
    },
    {
      "name": "战熄潮平",
      "desc": "战斗开始时，我方施放战技攻击敌方目标后，对每个被攻击的敌方目标造成固定数值的伤害。",
      "param": [
        0.55
      ]
    },
    {
      "name": "战意汹涌",
      "desc": "进入「战意汹涌」时，我方全体行动提前<color=#f29e38ff><unbreak>#1[i]%</unbreak></color>，期间敌方目标受到的伤害提高<color=#f29e38ff><unbreak>#2[i]%</unbreak></color>，且我方施放战技攻击敌方目标后，额外对每个被攻击的敌方目标的相邻目标造成固定数值的伤害。",
      "param": [
        1,
        0.5,
        0.55
      ]
    }
  ],
  "begin_time": "",
  "end_time": "",
  "level": [
    {
      "id": 20111,
      "name": "深文巧诋其一",
      "challenge": [
        {
          "name": "获得#1分",
          "param": 40000
        },
        {
          "name": "获得#1分",
          "param": 50000
        },
        {
          "name": "获得#1分",
          "param": 60000
        }
      ],
      "damage_type1": [
        "Ice",
        "Thunder"
      ],
      "damage_type2": [
        "Physical",
        "Imaginary"
      ],
      "maze_group_id1": 9,
      "maze_group_id2": 10,
      "npc_monster_id_list1": [
        2023030
      ],
      "npc_monster_id_list2": [
        2013020
      ],
      "event_id_list1": [
        {
          "stage_id": 30309011,
          "stage_type": "Challenge",
          "stage_name": 7086853316639384589,
          "hard_level_group": 1,
          "level": 55,
          "level_graph_path": "Config/Level/StageCommonTemplate.json",
          "stage_ability_config": [],
          "battle_scoring_group": 203,
          "sub_level_graphs": [],
          "stage_config_data": [
            {
              "jdkamoanicm": "_Wave",
              "mojjbfbkbnc": "3"
            },
            {
              "jdkamoanicm": "_IsEliteBattle",
              "mojjbfbkbnc": "1"
            },
            {
              "jdkamoanicm": "_StageInfiniteGroup",
              "mojjbfbkbnc": "30309011"
            },
            {
              "jdkamoanicm": "_CreateBattleEvent",
              "mojjbfbkbnc": "31001"
            },
            {
              "jdkamoanicm": "_ChallengeStoryType",
              "mojjbfbkbnc": "2"
            }
          ],
          "monster_list": [
            {
              "monster0": 3002010,
              "monster1": 8012030,
              "monster2": 300205006,
              "monster3": 3002010,
              "monster4": 8012030
            },
            {
              "monster0": 202303016
            },
            {
              "monster0": 202303016
            }
          ],
          "level_lose_condition": [],
          "level_win_condition": [],
          "release": true,
          "forbid_exit_battle": true,
          "monster_warning_ratio": 1.1,
          "trial_avatar_list": []
        }
      ],
      "event_id_list2": [
        {
          "stage_id": 30309012,
          "stage_type": "Challenge",
          "stage_name": 17363227603743607405,
          "hard_level_group": 1,
          "level": 55,
          "level_graph_path": "Config/Level/StageCommonTemplate.json",
          "stage_ability_config": [],
          "battle_scoring_group": 203,
          "sub_level_graphs": [],
          "stage_config_data": [
            {
              "jdkamoanicm": "_Wave",
              "mojjbfbkbnc": "3"
            },
            {
              "jdkamoanicm": "_IsEliteBattle",
              "mojjbfbkbnc": "1"
            },
            {
              "jdkamoanicm": "_StageInfiniteGroup",
              "mojjbfbkbnc": "30309012"
            },
            {
              "jdkamoanicm": "_CreateBattleEvent",
              "mojjbfbkbnc": "31001"
            },
            {
              "jdkamoanicm": "_ChallengeStoryType",
              "mojjbfbkbnc": "2"
            }
          ],
          "monster_list": [
            {
              "monster0": 1022020,
              "monster1": 1002030,
              "monster2": 300205006,
              "monster3": 1022020,
              "monster4": 1002030
            },
            {
              "monster0": 201302012
            },
            {
              "monster0": 201302012
            }
          ],
          "level_lose_condition": [],
          "level_win_condition": [],
          "release": true,
          "forbid_exit_battle": true,
          "monster_warning_ratio": 1.1,
          "trial_avatar_list": []
        }
      ],
      "infinite_list1": {
        "303090111": {
          "infinite_wave_id": 303090111,
          "monster_group_id_list": [
            8003060,
            3002010,
            8012030,
            300205006,
            3002010,
            8012030,
            3002010,
            8012030,
            3002010,
            8012030,
            300205006,
            3002010,
            8012030,
            3002010,
            8012030,
            3002010,
            8012030,
            300205006,
            3002010,
            8012030,
            3002010,
            8012030,
            3002010,
            8012030,
            3002010,
            8012030
          ],
          "max_monster_count": 25,
          "max_teammate_count": 5,
          "ability": "FantasticStory_Wave_Ability_0001",
          "param_list": [
            0,
            0
          ],
          "clear_previous_ability": true,
          "elite_group": 55
        },
        "303090112": {
          "infinite_wave_id": 303090112,
          "monster_group_id_list": [
            1012030,
            3012020,
            101302032,
            1012030,
            3012020,
            1012030,
            3012020,
            1012030,
            3012020,
            1012030,
            3012020,
            1012030,
            3012020,
            1012030,
            3012020,
            1012030,
            3012020,
            1012030,
            3012020,
            1012030,
            3012020,
            1012030,
            3012020,
            1012030,
            3012020,
            1012030,
            3012020,
            1012030,
            3012020,
            1012030,
            3012020,
            1012030,
            3012020,
            1012030,
            3012020,
            1012030,
            3012020,
            1012030,
            3012020,
            1012030,
            3012020
          ],
          "max_monster_count": 41,
          "max_teammate_count": 5,
          "ability": "FantasticStory_Wave_Ability_0001",
          "param_list": [
            0,
            1
          ],
          "clear_previous_ability": true,
          "elite_group": 55
        },
        "303090113": {
          "infinite_wave_id": 303090113,
          "monster_group_id_list": [
            2022060,
            2002030,
            202303016,
            2022060,
            2002030,
            2022060,
            2002030,
            2022060,
            2002030,
            2022060,
            2002030,
            2022060,
            2002030,
            2022060,
            2002030,
            2022060,
            2002030,
            2022060,
            2002030,
            2022060,
            2002030,
            2022060,
            2002030,
            2022060,
            2002030,
            2022060,
            2002030,
            2022060,
            2002030,
            2022060,
            2002030,
            2022060,
            2002030,
            2022060,
            2002030,
            2022060,
            2002030,
            2022060,
            2002030,
            2022060,
            2002030
          ],
          "max_monster_count": 41,
          "max_teammate_count": 5,
          "ability": "FantasticStory_Wave_Ability_0001",
          "param_list": [
            0.1,
            3.8
          ],
          "clear_previous_ability": true,
          "elite_group": 55
        }
      },
      "infinite_list2": {
        "303090121": {
          "infinite_wave_id": 303090121,
          "monster_group_id_list": [
            8003060,
            1022020,
            1002030,
            300205006,
            1022020,
            1002030,
            1022020,
            1002030,
            1022020,
            1002030,
            300205006,
            1022020,
            1002030,
            1022020,
            1002030,
            1022020,
            1002030,
            300205006,
            1022020,
            1002030,
            1022020,
            1002030,
            1022020,
            1002030,
            1022020,
            1002030
          ],
          "max_monster_count": 25,
          "max_teammate_count": 5,
          "ability": "FantasticStory_Wave_Ability_0001",
          "param_list": [
            0,
            0
          ],
          "clear_previous_ability": true,
          "elite_group": 55
        },
        "303090122": {
          "infinite_wave_id": 303090122,
          "monster_group_id_list": [
            8012010,
            8032020,
            801301025,
            8012010,
            8032020,
            8012010,
            8032020,
            8012010,
            8032020,
            8012010,
            8032020,
            8012010,
            8032020,
            8012010,
            8032020,
            8012010,
            8032020,
            8012010,
            8032020,
            8012010,
            8032020,
            8012010,
            8032020,
            8012010,
            8032020,
            8012010,
            8032020,
            8012010,
            8032020,
            8012010,
            8032020,
            8012010,
            8032020,
            8012010,
            8032020,
            8012010,
            8032020,
            8012010,
            8032020,
            8012010,
            8032020
          ],
          "max_monster_count": 41,
          "max_teammate_count": 5,
          "ability": "FantasticStory_Wave_Ability_0001",
          "param_list": [
            0,
            1
          ],
          "clear_previous_ability": true,
          "elite_group": 55
        },
        "303090123": {
          "infinite_wave_id": 303090123,
          "monster_group_id_list": [
            2012010,
            2032010,
            201302012,
            2012010,
            2032010,
            2012010,
            2032010,
            2012010,
            2032010,
            2012010,
            2032010,
            2012010,
            2032010,
            2012010,
            2032010,
            2012010,
            2032010,
            2012010,
            2032010,
            2012010,
            2032010,
            2012010,
            2032010,
            2012010,
            2032010,
            2012010,
            2032010,
            2012010,
            2032010,
            2012010,
            2032010,
            2012010,
            2032010,
            2012010,
            2032010,
            2012010,
            2032010,
            2012010,
            2032010,
            2012010,
            2032010
          ],
          "max_monster_count": 41,
          "max_teammate_count": 5,
          "ability": "FantasticStory_Wave_Ability_0001",
          "param_list": [
            0.1,
            3.8
          ],
          "clear_previous_ability": true,
          "elite_group": 55
        }
      }
    },
    {
      "id": 20112,
      "name": "深文巧诋其二",
      "challenge": [
        {
          "name": "获得#1分",
          "param": 40000
        },
        {
          "name": "获得#1分",
          "param": 50000
        },
        {
          "name": "获得#1分",
          "param": 60000
        }
      ],
      "damage_type1": [
        "Fire",
        "Imaginary"
      ],
      "damage_type2": [
        "Ice",
        "Quantum"
      ],
      "maze_group_id1": 9,
      "maze_group_id2": 10,
      "npc_monster_id_list1": [
        3003030
      ],
      "npc_monster_id_list2": [
        1003010
      ],
      "event_id_list1": [
        {
          "stage_id": 30309021,
          "stage_type": "Challenge",
          "stage_name": 18110657579897695596,
          "hard_level_group": 1,
          "level": 65,
          "level_graph_path": "Config/Level/StageCommonTemplate.json",
          "stage_ability_config": [],
          "battle_scoring_group": 203,
          "sub_level_graphs": [],
          "stage_config_data": [
            {
              "jdkamoanicm": "_Wave",
              "mojjbfbkbnc": "3"
            },
            {
              "jdkamoanicm": "_IsEliteBattle",
              "mojjbfbkbnc": "1"
            },
            {
              "jdkamoanicm": "_StageInfiniteGroup",
              "mojjbfbkbnc": "30309021"
            },
            {
              "jdkamoanicm": "_CreateBattleEvent",
              "mojjbfbkbnc": "31001"
            },
            {
              "jdkamoanicm": "_ChallengeStoryType",
              "mojjbfbkbnc": "2"
            }
          ],
          "monster_list": [
            {
              "monster0": 2032010,
              "monster1": 202205004,
              "monster2": 300205006,
              "monster3": 2032010,
              "monster4": 202205004
            },
            {
              "monster0": 300303006
            },
            {
              "monster0": 300303006
            }
          ],
          "level_lose_condition": [],
          "level_win_condition": [],
          "release": true,
          "forbid_exit_battle": true,
          "monster_warning_ratio": 1.1,
          "trial_avatar_list": []
        }
      ],
      "event_id_list2": [
        {
          "stage_id": 30309022,
          "stage_type": "Challenge",
          "stage_name": 9874079526424322448,
          "hard_level_group": 1,
          "level": 65,
          "level_graph_path": "Config/Level/StageCommonTemplate.json",
          "stage_ability_config": [],
          "battle_scoring_group": 203,
          "sub_level_graphs": [],
          "stage_config_data": [
            {
              "jdkamoanicm": "_Wave",
              "mojjbfbkbnc": "3"
            },
            {
              "jdkamoanicm": "_IsEliteBattle",
              "mojjbfbkbnc": "1"
            },
            {
              "jdkamoanicm": "_StageInfiniteGroup",
              "mojjbfbkbnc": "30309022"
            },
            {
              "jdkamoanicm": "_CreateBattleEvent",
              "mojjbfbkbnc": "31001"
            },
            {
              "jdkamoanicm": "_ChallengeStoryType",
              "mojjbfbkbnc": "2"
            }
          ],
          "monster_list": [
            {
              "monster0": 8012030,
              "monster1": 2022110,
              "monster2": 300205006,
              "monster3": 8012030,
              "monster4": 2022110
            },
            {
              "monster0": 100301035
            },
            {
              "monster0": 100301035
            }
          ],
          "level_lose_condition": [],
          "level_win_condition": [],
          "release": true,
          "forbid_exit_battle": true,
          "monster_warning_ratio": 1.1,
          "trial_avatar_list": []
        }
      ],
      "infinite_list1": {
        "303090211": {
          "infinite_wave_id": 303090211,
          "monster_group_id_list": [
            8003060,
            2032010,
            202205004,
            300205006,
            2032010,
            202205004,
            2032010,
            202205004,
            2032010,
            202205004,
            300205006,
            2032010,
            202205004,
            2032010,
            202205004,
            2032010,
            202205004,
            300205006,
            2032010,
            202205004,
            2032010,
            202205004,
            2032010,
            202205004,
            2032010,
            202205004
          ],
          "max_monster_count": 25,
          "max_teammate_count": 5,
          "ability": "FantasticStory_Wave_Ability_0001",
          "param_list": [
            0,
            0
          ],
          "clear_previous_ability": true,
          "elite_group": 56
        },
        "303090212": {
          "infinite_wave_id": 303090212,
          "monster_group_id_list": [
            8032010,
            8032020,
            803301011,
            8032010,
            8032020,
            8032010,
            8032020,
            8032010,
            8032020,
            8032010,
            8032020,
            8032010,
            8032020,
            8032010,
            8032020,
            8032010,
            8032020,
            8032010,
            8032020,
            8032010,
            8032020,
            8032010,
            8032020,
            8032010,
            8032020,
            8032010,
            8032020,
            8032010,
            8032020,
            8032010,
            8032020,
            8032010,
            8032020,
            8032010,
            8032020,
            8032010,
            8032020,
            8032010,
            8032020,
            8032010,
            8032020
          ],
          "max_monster_count": 41,
          "max_teammate_count": 5,
          "ability": "FantasticStory_Wave_Ability_0001",
          "param_list": [
            0,
            1
          ],
          "clear_previous_ability": true,
          "elite_group": 56
        },
        "303090213": {
          "infinite_wave_id": 303090213,
          "monster_group_id_list": [
            2002010,
            1002020,
            300303006,
            2002010,
            1002020,
            2002010,
            1002020,
            2002010,
            1002020,
            2002010,
            1002020,
            2002010,
            1002020,
            2002010,
            1002020,
            2002010,
            1002020,
            2002010,
            1002020,
            2002010,
            1002020,
            2002010,
            1002020,
            2002010,
            1002020,
            2002010,
            1002020,
            2002010,
            1002020,
            2002010,
            1002020,
            2002010,
            1002020,
            2002010,
            1002020,
            2002010,
            1002020,
            2002010,
            1002020,
            2002010,
            1002020
          ],
          "max_monster_count": 41,
          "max_teammate_count": 5,
          "ability": "FantasticStory_Wave_Ability_0001",
          "param_list": [
            0.1,
            3.8
          ],
          "clear_previous_ability": true,
          "elite_group": 56
        }
      },
      "infinite_list2": {
        "303090221": {
          "infinite_wave_id": 303090221,
          "monster_group_id_list": [
            8003060,
            8012030,
            2022110,
            300205006,
            8012030,
            2022110,
            8012030,
            2022110,
            8012030,
            2022110,
            300205006,
            8012030,
            2022110,
            8012030,
            2022110,
            8012030,
            2022110,
            300205006,
            8012030,
            2022110,
            8012030,
            2022110,
            8012030,
            2022110,
            8012030,
            2022110
          ],
          "max_monster_count": 25,
          "max_teammate_count": 5,
          "ability": "FantasticStory_Wave_Ability_0001",
          "param_list": [
            0,
            0
          ],
          "clear_previous_ability": true,
          "elite_group": 56
        },
        "303090222": {
          "infinite_wave_id": 303090222,
          "monster_group_id_list": [
            2022110,
            2022010,
            800302023,
            2022110,
            2022010,
            2022110,
            2022010,
            2022110,
            2022010,
            2022110,
            2022010,
            2022110,
            2022010,
            2022110,
            2022010,
            2022110,
            2022010,
            2022110,
            2022010,
            2022110,
            2022010,
            2022110,
            2022010,
            2022110,
            2022010,
            2022110,
            2022010,
            2022110,
            2022010,
            2022110,
            2022010,
            2022110,
            2022010,
            2022110,
            2022010,
            2022110,
            2022010,
            2022110,
            2022010,
            2022110,
            2022010
          ],
          "max_monster_count": 41,
          "max_teammate_count": 5,
          "ability": "FantasticStory_Wave_Ability_0001",
          "param_list": [
            0,
            1
          ],
          "clear_previous_ability": true,
          "elite_group": 56
        },
        "303090223": {
          "infinite_wave_id": 303090223,
          "monster_group_id_list": [
            1002040,
            1002030,
            100301035,
            1002040,
            1002030,
            1002040,
            1002030,
            1002040,
            1002030,
            1002040,
            1002030,
            1002040,
            1002030,
            1002040,
            1002030,
            1002040,
            1002030,
            1002040,
            1002030,
            1002040,
            1002030,
            1002040,
            1002030,
            1002040,
            1002030,
            1002040,
            1002030,
            1002040,
            1002030,
            1002040,
            1002030,
            1002040,
            1002030,
            1002040,
            1002030,
            1002040,
            1002030,
            1002040,
            1002030,
            1002040,
            1002030
          ],
          "max_monster_count": 41,
          "max_teammate_count": 5,
          "ability": "FantasticStory_Wave_Ability_0001",
          "param_list": [
            0.1,
            3.8
          ],
          "clear_previous_ability": true,
          "elite_group": 56
        }
      }
    },
    {
      "id": 20113,
      "name": "深文巧诋其三",
      "challenge": [
        {
          "name": "获得#1分",
          "param": 40000
        },
        {
          "name": "获得#1分",
          "param": 50000
        },
        {
          "name": "获得#1分",
          "param": 60000
        }
      ],
      "damage_type1": [
        "Ice",
        "Thunder"
      ],
      "damage_type2": [
        "Physical",
        "Imaginary"
      ],
      "maze_group_id1": 9,
      "maze_group_id2": 10,
      "npc_monster_id_list1": [
        2023030
      ],
      "npc_monster_id_list2": [
        2013020
      ],
      "event_id_list1": [
        {
          "stage_id": 30309031,
          "stage_type": "Challenge",
          "stage_name": 7086853316639384589,
          "hard_level_group": 1,
          "level": 75,
          "level_graph_path": "Config/Level/StageCommonTemplate.json",
          "stage_ability_config": [],
          "battle_scoring_group": 203,
          "sub_level_graphs": [],
          "stage_config_data": [
            {
              "jdkamoanicm": "_Wave",
              "mojjbfbkbnc": "3"
            },
            {
              "jdkamoanicm": "_IsEliteBattle",
              "mojjbfbkbnc": "1"
            },
            {
              "jdkamoanicm": "_StageInfiniteGroup",
              "mojjbfbkbnc": "30309031"
            },
            {
              "jdkamoanicm": "_CreateBattleEvent",
              "mojjbfbkbnc": "31001"
            },
            {
              "jdkamoanicm": "_ChallengeStoryType",
              "mojjbfbkbnc": "2"
            }
          ],
          "monster_list": [
            {
              "monster0": 3002010,
              "monster1": 8012030,
              "monster2": 300205006,
              "monster3": 3002010,
              "monster4": 8012030
            },
            {
              "monster0": 202303016
            },
            {
              "monster0": 202303016
            }
          ],
          "level_lose_condition": [],
          "level_win_condition": [],
          "release": true,
          "forbid_exit_battle": true,
          "monster_warning_ratio": 1.1,
          "trial_avatar_list": []
        }
      ],
      "event_id_list2": [
        {
          "stage_id": 30309032,
          "stage_type": "Challenge",
          "stage_name": 17363227603743607405,
          "hard_level_group": 1,
          "level": 75,
          "level_graph_path": "Config/Level/StageCommonTemplate.json",
          "stage_ability_config": [],
          "battle_scoring_group": 203,
          "sub_level_graphs": [],
          "stage_config_data": [
            {
              "jdkamoanicm": "_Wave",
              "mojjbfbkbnc": "3"
            },
            {
              "jdkamoanicm": "_IsEliteBattle",
              "mojjbfbkbnc": "1"
            },
            {
              "jdkamoanicm": "_StageInfiniteGroup",
              "mojjbfbkbnc": "30309032"
            },
            {
              "jdkamoanicm": "_CreateBattleEvent",
              "mojjbfbkbnc": "31001"
            },
            {
              "jdkamoanicm": "_ChallengeStoryType",
              "mojjbfbkbnc": "2"
            }
          ],
          "monster_list": [
            {
              "monster0": 1022020,
              "monster1": 1002030,
              "monster2": 300205006,
              "monster3": 1022020,
              "monster4": 1002030
            },
            {
              "monster0": 201302012
            },
            {
              "monster0": 201302012
            }
          ],
          "level_lose_condition": [],
          "level_win_condition": [],
          "release": true,
          "forbid_exit_battle": true,
          "monster_warning_ratio": 1.1,
          "trial_avatar_list": []
        }
      ],
      "infinite_list1": {
        "303090311": {
          "infinite_wave_id": 303090311,
          "monster_group_id_list": [
            8003060,
            3002010,
            8012030,
            300205006,
            3002010,
            8012030,
            3002010,
            8012030,
            3002010,
            8012030,
            300205006,
            3002010,
            8012030,
            3002010,
            8012030,
            3002010,
            8012030,
            300205006,
            3002010,
            8012030,
            3002010,
            8012030,
            3002010,
            8012030,
            3002010,
            8012030
          ],
          "max_monster_count": 25,
          "max_teammate_count": 5,
          "ability": "FantasticStory_Wave_Ability_0001",
          "param_list": [
            0,
            0
          ],
          "clear_previous_ability": true,
          "elite_group": 57
        },
        "303090312": {
          "infinite_wave_id": 303090312,
          "monster_group_id_list": [
            1012030,
            3012020,
            101302032,
            1012030,
            3012020,
            1012030,
            3012020,
            1012030,
            3012020,
            1012030,
            3012020,
            1012030,
            3012020,
            1012030,
            3012020,
            1012030,
            3012020,
            1012030,
            3012020,
            1012030,
            3012020,
            1012030,
            3012020,
            1012030,
            3012020,
            1012030,
            3012020,
            1012030,
            3012020,
            1012030,
            3012020,
            1012030,
            3012020,
            1012030,
            3012020,
            1012030,
            3012020,
            1012030,
            3012020,
            1012030,
            3012020
          ],
          "max_monster_count": 41,
          "max_teammate_count": 5,
          "ability": "FantasticStory_Wave_Ability_0001",
          "param_list": [
            0,
            1
          ],
          "clear_previous_ability": true,
          "elite_group": 57
        },
        "303090313": {
          "infinite_wave_id": 303090313,
          "monster_group_id_list": [
            2022060,
            2002030,
            202303016,
            2022060,
            2002030,
            2022060,
            2002030,
            2022060,
            2002030,
            2022060,
            2002030,
            2022060,
            2002030,
            2022060,
            2002030,
            2022060,
            2002030,
            2022060,
            2002030,
            2022060,
            2002030,
            2022060,
            2002030,
            2022060,
            2002030,
            2022060,
            2002030,
            2022060,
            2002030,
            2022060,
            2002030,
            2022060,
            2002030,
            2022060,
            2002030,
            2022060,
            2002030,
            2022060,
            2002030,
            2022060,
            2002030
          ],
          "max_monster_count": 41,
          "max_teammate_count": 5,
          "ability": "FantasticStory_Wave_Ability_0001",
          "param_list": [
            0.1,
            3.8
          ],
          "clear_previous_ability": true,
          "elite_group": 57
        }
      },
      "infinite_list2": {
        "303090321": {
          "infinite_wave_id": 303090321,
          "monster_group_id_list": [
            8003060,
            1022020,
            1002030,
            300205006,
            1022020,
            1002030,
            1022020,
            1002030,
            1022020,
            1002030,
            300205006,
            1022020,
            1002030,
            1022020,
            1002030,
            1022020,
            1002030,
            300205006,
            1022020,
            1002030,
            1022020,
            1002030,
            1022020,
            1002030,
            1022020,
            1002030
          ],
          "max_monster_count": 25,
          "max_teammate_count": 5,
          "ability": "FantasticStory_Wave_Ability_0001",
          "param_list": [
            0,
            0
          ],
          "clear_previous_ability": true,
          "elite_group": 57
        },
        "303090322": {
          "infinite_wave_id": 303090322,
          "monster_group_id_list": [
            8012010,
            8032020,
            801301025,
            8012010,
            8032020,
            8012010,
            8032020,
            8012010,
            8032020,
            8012010,
            8032020,
            8012010,
            8032020,
            8012010,
            8032020,
            8012010,
            8032020,
            8012010,
            8032020,
            8012010,
            8032020,
            8012010,
            8032020,
            8012010,
            8032020,
            8012010,
            8032020,
            8012010,
            8032020,
            8012010,
            8032020,
            8012010,
            8032020,
            8012010,
            8032020,
            8012010,
            8032020,
            8012010,
            8032020,
            8012010,
            8032020
          ],
          "max_monster_count": 41,
          "max_teammate_count": 5,
          "ability": "FantasticStory_Wave_Ability_0001",
          "param_list": [
            0,
            1
          ],
          "clear_previous_ability": true,
          "elite_group": 57
        },
        "303090323": {
          "infinite_wave_id": 303090323,
          "monster_group_id_list": [
            2012010,
            2032010,
            201302012,
            2012010,
            2032010,
            2012010,
            2032010,
            2012010,
            2032010,
            2012010,
            2032010,
            2012010,
            2032010,
            2012010,
            2032010,
            2012010,
            2032010,
            2012010,
            2032010,
            2012010,
            2032010,
            2012010,
            2032010,
            2012010,
            2032010,
            2012010,
            2032010,
            2012010,
            2032010,
            2012010,
            2032010,
            2012010,
            2032010,
            2012010,
            2032010,
            2012010,
            2032010,
            2012010,
            2032010,
            2012010,
            2032010
          ],
          "max_monster_count": 41,
          "max_teammate_count": 5,
          "ability": "FantasticStory_Wave_Ability_0001",
          "param_list": [
            0.1,
            3.8
          ],
          "clear_previous_ability": true,
          "elite_group": 57
        }
      }
    },
    {
      "id": 20114,
      "name": "深文巧诋其四",
      "challenge": [
        {
          "name": "获得#1分",
          "param": 40000
        },
        {
          "name": "获得#1分",
          "param": 50000
        },
        {
          "name": "获得#1分",
          "param": 60000
        }
      ],
      "damage_type1": [
        "Thunder",
        "Imaginary"
      ],
      "damage_type2": [
        "Fire",
        "Ice"
      ],
      "maze_group_id1": 9,
      "maze_group_id2": 10,
      "npc_monster_id_list1": [
        1004020
      ],
      "npc_monster_id_list2": [
        2024010
      ],
      "event_id_list1": [
        {
          "stage_id": 30309041,
          "stage_type": "Challenge",
          "stage_name": 3927571639738101840,
          "hard_level_group": 1,
          "level": 85,
          "level_graph_path": "Config/Level/StageCommonTemplate.json",
          "stage_ability_config": [],
          "battle_scoring_group": 203,
          "sub_level_graphs": [],
          "stage_config_data": [
            {
              "jdkamoanicm": "_Wave",
              "mojjbfbkbnc": "3"
            },
            {
              "jdkamoanicm": "_IsEliteBattle",
              "mojjbfbkbnc": "1"
            },
            {
              "jdkamoanicm": "_StageInfiniteGroup",
              "mojjbfbkbnc": "30309041"
            },
            {
              "jdkamoanicm": "_CreateBattleEvent",
              "mojjbfbkbnc": "31001"
            },
            {
              "jdkamoanicm": "_ChallengeStoryType",
              "mojjbfbkbnc": "2"
            }
          ],
          "monster_list": [
            {
              "monster0": 1012030,
              "monster1": 2012010,
              "monster2": 300205006,
              "monster3": 1012030,
              "monster4": 2012010
            },
            {
              "monster0": 100402014
            },
            {
              "monster0": 100402014
            }
          ],
          "level_lose_condition": [],
          "level_win_condition": [],
          "release": true,
          "forbid_exit_battle": true,
          "monster_warning_ratio": 1.1,
          "trial_avatar_list": []
        }
      ],
      "event_id_list2": [
        {
          "stage_id": 30309042,
          "stage_type": "Challenge",
          "stage_name": 14388894098916908856,
          "hard_level_group": 1,
          "level": 85,
          "level_graph_path": "Config/Level/StageCommonTemplate.json",
          "stage_ability_config": [],
          "battle_scoring_group": 203,
          "sub_level_graphs": [],
          "stage_config_data": [
            {
              "jdkamoanicm": "_Wave",
              "mojjbfbkbnc": "3"
            },
            {
              "jdkamoanicm": "_IsEliteBattle",
              "mojjbfbkbnc": "1"
            },
            {
              "jdkamoanicm": "_StageInfiniteGroup",
              "mojjbfbkbnc": "30309042"
            },
            {
              "jdkamoanicm": "_CreateBattleEvent",
              "mojjbfbkbnc": "31001"
            },
            {
              "jdkamoanicm": "_ChallengeStoryType",
              "mojjbfbkbnc": "2"
            }
          ],
          "monster_list": [
            {
              "monster0": 1002020,
              "monster1": 2022060,
              "monster2": 300205006,
              "monster3": 1002020,
              "monster4": 2022060
            },
            {
              "monster0": 202401406
            },
            {
              "monster0": 202401406
            }
          ],
          "level_lose_condition": [],
          "level_win_condition": [],
          "release": true,
          "forbid_exit_battle": true,
          "monster_warning_ratio": 1.1,
          "trial_avatar_list": []
        }
      ],
      "infinite_list1": {
        "303090411": {
          "infinite_wave_id": 303090411,
          "monster_group_id_list": [
            8003060,
            1012030,
            2012010,
            300205006,
            1012030,
            2012010,
            1012030,
            2012010,
            1012030,
            2012010,
            300205006,
            1012030,
            2012010,
            1012030,
            2012010,
            1012030,
            2012010,
            300205006,
            1012030,
            2012010,
            1012030,
            2012010,
            1012030,
            2012010,
            1012030,
            2012010
          ],
          "max_monster_count": 25,
          "max_teammate_count": 5,
          "ability": "FantasticStory_Wave_Ability_0001",
          "param_list": [
            0,
            0
          ],
          "clear_previous_ability": true,
          "elite_group": 57
        },
        "303090412": {
          "infinite_wave_id": 303090412,
          "monster_group_id_list": [
            2032010,
            1022020,
            300303006,
            2032010,
            1022020,
            2032010,
            1022020,
            2032010,
            1022020,
            2032010,
            1022020,
            2032010,
            1022020,
            2032010,
            1022020,
            2032010,
            1022020,
            2032010,
            1022020,
            2032010,
            1022020,
            2032010,
            1022020,
            2032010,
            1022020,
            2032010,
            1022020,
            2032010,
            1022020,
            2032010,
            1022020,
            2032010,
            1022020,
            2032010,
            1022020,
            2032010,
            1022020,
            2032010,
            1022020,
            2032010,
            1022020
          ],
          "max_monster_count": 41,
          "max_teammate_count": 5,
          "ability": "FantasticStory_Wave_Ability_0001",
          "param_list": [
            0,
            1.6
          ],
          "clear_previous_ability": true,
          "elite_group": 57
        },
        "303090413": {
          "infinite_wave_id": 303090413,
          "monster_group_id_list": [
            1012010,
            1002030,
            100402014,
            1012010,
            1002030,
            1012010,
            1002030,
            1012010,
            1002030,
            1012010,
            1002030,
            1012010,
            1002030,
            1012010,
            1002030,
            1012010,
            1002030,
            1012010,
            1002030,
            1012010,
            1002030,
            1012010,
            1002030,
            1012010,
            1002030,
            1012010,
            1002030,
            1012010,
            1002030,
            1012010,
            1002030,
            1012010,
            1002030,
            1012010,
            1002030,
            1012010,
            1002030,
            1012010,
            1002030,
            1012010,
            1002030
          ],
          "max_monster_count": 41,
          "max_teammate_count": 5,
          "ability": "FantasticStory_Wave_Ability_0001",
          "param_list": [
            0.1,
            5.4
          ],
          "clear_previous_ability": true,
          "elite_group": 57
        }
      },
      "infinite_list2": {
        "303090421": {
          "infinite_wave_id": 303090421,
          "monster_group_id_list": [
            8003060,
            1002020,
            2022060,
            300205006,
            1002020,
            2022060,
            1002020,
            2022060,
            1002020,
            2022060,
            300205006,
            1002020,
            2022060,
            1002020,
            2022060,
            1002020,
            2022060,
            300205006,
            1002020,
            2022060,
            1002020,
            2022060,
            1002020,
            2022060,
            1002020,
            2022060
          ],
          "max_monster_count": 25,
          "max_teammate_count": 5,
          "ability": "FantasticStory_Wave_Ability_0001",
          "param_list": [
            0,
            0
          ],
          "clear_previous_ability": true,
          "elite_group": 57
        },
        "303090422": {
          "infinite_wave_id": 303090422,
          "monster_group_id_list": [
            8032010,
            8032020,
            803301011,
            8032010,
            8032020,
            8032010,
            8032020,
            8032010,
            8032020,
            8032010,
            8032020,
            8032010,
            8032020,
            8032010,
            8032020,
            8032010,
            8032020,
            8032010,
            8032020,
            8032010,
            8032020,
            8032010,
            8032020,
            8032010,
            8032020,
            8032010,
            8032020,
            8032010,
            8032020,
            8032010,
            8032020,
            8032010,
            8032020,
            8032010,
            8032020,
            8032010,
            8032020,
            8032010,
            8032020,
            8032010,
            8032020
          ],
          "max_monster_count": 41,
          "max_teammate_count": 5,
          "ability": "FantasticStory_Wave_Ability_0001",
          "param_list": [
            0,
            1.6
          ],
          "clear_previous_ability": true,
          "elite_group": 57
        },
        "303090423": {
          "infinite_wave_id": 303090423,
          "monster_group_id_list": [
            2022080,
            2022090,
            202401406,
            2022080,
            2022090,
            2022080,
            2022090,
            2022080,
            2022090,
            2022080,
            2022090,
            2022080,
            2022090,
            2022080,
            2022090,
            2022080,
            2022090,
            2022080,
            2022090,
            2022080,
            2022090,
            2022080,
            2022090,
            2022080,
            2022090,
            2022080,
            2022090,
            2022080,
            2022090,
            2022080,
            2022090,
            2022080,
            2022090,
            2022080,
            2022090,
            2022080,
            2022090,
            2022080,
            2022090,
            2022080,
            2022090
          ],
          "max_monster_count": 41,
          "max_teammate_count": 5,
          "ability": "FantasticStory_Wave_Ability_0001",
          "param_list": [
            0.1,
            4
          ],
          "clear_previous_ability": true,
          "elite_group": 57
        }
      }
    }
  ]
}